LICENSE
flask_whooshalchemy3/__init__.py
flask_whooshalchemy3-0.3.0.dist-info/LICENSE
flask_whooshalchemy3-0.3.0.dist-info/WHEEL
flask_whooshalchemy3-0.3.0.dist-info/METADATA
flask_whooshalchemy3-0.3.0.dist-info/RECORD
