Metadata-Version: 2.1
Name: flask-whooshalchemy3
Version: 0.3.0
Summary: Whoosh indexing capabilities for Flask-SQLAlchemy, Python 3 compatibility fork.
Home-page: https://github.com/blakev/Flask-WhooshAlchemy3
License: MIT
Keywords: search,orm,flask,whoosh,sqlalchemy
Author: Blake VandeMerwe
Author-email: blakev@null.net
Requires-Python: >=3.6.1,<4.0.0
Classifier: License :: OSI Approved :: MIT License
Classifier: Programming Language :: Python :: 3
Classifier: Programming Language :: Python :: 3.7
Classifier: Programming Language :: Python :: 3.8
Classifier: Programming Language :: Python :: 3.9
Requires-Dist: Flask (>=1.1)
Requires-Dist: Flask-SQLAlchemy (>=2.5.1,<3.0.0)
Requires-Dist: SQLAlchemy (>=1.4,<1.4.23)
Requires-Dist: Whoosh (>=2.7)
Requires-Dist: blinker (>=1.4,<2.0)
Project-URL: Repository, https://github.com/blakev/Flask-WhooshAlchemy3.git
